sphinx_pydata_theme/__init__.py
sphinx_pydata_theme-0.1.0.dist-info/METADATA
sphinx_pydata_theme-0.1.0.dist-info/WHEEL
sphinx_pydata_theme-0.1.0.dist-info/top_level.txt
sphinx_pydata_theme-0.1.0.dist-info/RECORD
