Metadata-Version: 2.2
Name: sphinx_pydata_theme
Version: 0.1.0
Summary: A minimal example Python package
Requires-Python: >=3.6
